{
  "comment": "This file is generated by node-scripts-docs.",
  "scripts": [
    {
      "manifestPath": "package.json",
      "projectName": "yarn3-monorepo",
      "scriptName": "build",
      "scriptCode": "snowpack build",
      "isGlobal": false,
      "isRootManifest": true
    },
    {
      "manifestPath": "packages/documentation/package.json",
      "projectName": "documentation",
      "scriptName": "docs:build",
      "scriptCode": ".scripts/build.sh",
      "isGlobal": true,
      "isRootManifest": false
    },
    {
      "manifestPath": "package.json",
      "projectName": "yarn3-monorepo",
      "scriptName": "docs:scripts:build",
      "scriptCode": "nsd --docs-location \"packages/documentation/docs/reference/Repository Scripts/\"",
      "isGlobal": true,
      "isRootManifest": true
    },
    {
      "manifestPath": "package.json",
      "projectName": "yarn3-monorepo",
      "scriptName": "docs:scripts:check",
      "scriptCode": "nsd --docs-location \"packages/documentation/docs/reference/Repository Scripts/\" --check-only",
      "isGlobal": true,
      "isRootManifest": true
    },
    {
      "manifestPath": "packages/documentation/package.json",
      "projectName": "documentation",
      "scriptName": "docs:serve",
      "scriptCode": ".scripts/serve.sh",
      "isGlobal": true,
      "isRootManifest": false
    },
    {
      "manifestPath": "package.json",
      "projectName": "yarn3-monorepo",
      "scriptName": "lint:eslint",
      "scriptCode": "eslint source",
      "isGlobal": true,
      "isRootManifest": true
    },
    {
      "manifestPath": "package.json",
      "projectName": "yarn3-monorepo",
      "scriptName": "lint:tsc",
      "scriptCode": "tsc --noEmit",
      "isGlobal": true,
      "isRootManifest": true
    },
    {
      "manifestPath": "package.json",
      "projectName": "yarn3-monorepo",
      "scriptName": "serve",
      "scriptCode": "snowpack dev",
      "isGlobal": false,
      "isRootManifest": true
    }
  ],
  "version": 1
}
